{
	"info": {
		"_postman_id": "d6ab8dbb-03ab-49a7-9a8a-5f54676315f8",
		"name": "Testing",
		"schema": "https://schema.getpostman.com/json/collection/v2.1.0/collection.json",
		"_exporter_id": "34864685",
		"_collection_link": "https://adishi.postman.co/workspace/7cc1a8b9-327a-48e2-9269-9b4e7975b09d/collection/34864685-d6ab8dbb-03ab-49a7-9a8a-5f54676315f8?action=share&source=collection_link&creator=34864685"
	},
	"item": [
		{
			"name": "Login",
			"request": {
				"method": "POST",
				"header": [],
				"body": {
					"mode": "raw",
					"raw": "{\n    \"name\":\"dwyn\",\n    \"email\":\"dwyn@mail.com\",\n    \"password\":\"1234\"\n}",
					"options": {
						"raw": {
							"language": "json"
						}
					}
				},
				"url": {
					"raw": "http://localhost:3000/api/auth/register",
					"protocol": "http",
					"host": [
						"localhost"
					],
					"port": "3000",
					"path": [
						"api",
						"auth",
						"register"
					]
				}
			},
			"response": []
		},
		{
			"name": "Register",
			"request": {
				"method": "POST",
				"header": [],
				"url": {
					"raw": "http://localhost:3001/api/auth/register",
					"protocol": "http",
					"host": [
						"localhost"
					],
					"port": "3001",
					"path": [
						"api",
						"auth",
						"register"
					]
				}
			},
			"response": []
		},
		{
			"name": "Get All Posts",
			"request": {
				"method": "GET",
				"header": [],
				"url": {
					"raw": "http://localhost:3001/api/posts",
					"protocol": "http",
					"host": [
						"localhost"
					],
					"port": "3001",
					"path": [
						"api",
						"posts"
					]
				}
			},
			"response": []
		}
	]
}